symile/__init__.py
symile/loss.py
symile/similarity.py
symile-0.1.0.dist-info/LICENSE
symile-0.1.0.dist-info/METADATA
symile-0.1.0.dist-info/WHEEL
symile-0.1.0.dist-info/RECORD
