Metadata-Version: 2.1
Name: symile
Version: 0.1.0
Summary: Symile
Home-page: https://github.com/rajesh-lab/symile
License: MIT
Keywords: symile,multimodal,contrastive learning,clip
Author: Adriel Saporta
Author-email: adriel@nyu.edu
Requires-Python: >=3.9
Classifier: License :: OSI Approved :: MIT License
Classifier: Programming Language :: Python :: 3
Classifier: Programming Language :: Python :: 3.9
Classifier: Programming Language :: Python :: 3.10
Classifier: Programming Language :: Python :: 3.11
Classifier: Programming Language :: Python :: 3.12
Requires-Dist: numpy
Requires-Dist: torch (>=1.9.0)
Project-URL: Repository, https://github.com/rajesh-lab/symile
